LICENSE
README.md
setup.cfg
setup.py
luq/__init__.py
luq/version.py
luq.egg-info/PKG-INFO
luq.egg-info/SOURCES.txt
luq.egg-info/dependency_links.txt
luq.egg-info/requires.txt
luq.egg-info/top_level.txt
luq/datasets/__init__.py
luq/datasets/dataset.py
luq/evals/__init__.py
luq/evals/accuracy_eval.py
luq/evals/uncertainy_eval.py
luq/llm/__init__.py
luq/llm/llm.py
luq/llm/nli.py
luq/models/__init__.py
luq/models/base_uq_model.py
luq/models/conformal.py
luq/models/kernel_language_entropy.py
luq/models/kernel_utils.py
luq/models/max_probability.py
luq/models/p_true.py
luq/models/predictive_entropy.py
luq/models/semantic_entropy.py
luq/models/top_k_gap.py
luq/utils/__init__.py
luq/utils/utils.py
tests/test_datasets.py
tests/test_evals.py
tests/test_kernel_language_entropy.py
tests/test_kernel_utils.py
tests/test_max_probability.py
tests/test_nli.py
tests/test_p_true.py
tests/test_predictive_entropy_estimator.py
tests/test_scripts.py
tests/test_semantic_entropy.py
tests/test_top_k_gap.py
tests/test_utils.py