Metadata-Version: 2.1
Name: luq
Version: 0.0.2
Summary: Framework for uncertainty quantification of LLMs
Home-page: https://github.com/AlexanderVNikitin/luq
Download-URL: 
Author: Alexander Nikitin
Author-email: 
Maintainer: Alexander Nikitin
Maintainer-email: 
License: MIT
Keywords: machine learning,deep learning,natural language processing,uncertainty quantification,large language models
License-File: LICENSE
Requires-Dist: huggingface
Requires-Dist: loguru
Requires-Dist: scipy
Requires-Dist: tqdm
Requires-Dist: datasets
